malign/__init__.py
malign/__main__.py
malign/alignment.py
malign/anw.py
malign/dumb.py
malign/malign.py
malign/scoring_matrix.py
malign/utils.py
malign/yenksp.py
malign-0.3.2.data/data/docs/Align experiment.ipynb
malign-0.3.2.data/data/docs/Demo.ipynb
malign-0.3.2.data/data/docs/Malign.ipynb
malign-0.3.2.data/data/docs/devel.ipynb
malign-0.3.2.data/data/docs/ita_grk.matrix
malign-0.3.2.data/data/docs/ita_rus.matrix
malign-0.3.2.data/data/docs/ita_rus_grk.matrix
malign-0.3.2.data/data/resources/bdpa/README.md
malign-0.3.2.data/data/resources/bdpa/andean.tsv
malign-0.3.2.data/data/resources/bdpa/bai.tsv
malign-0.3.2.data/data/resources/bdpa/bulgarian.tsv
malign-0.3.2.data/data/resources/bdpa/dutch.tsv
malign-0.3.2.data/data/resources/bdpa/french.tsv
malign-0.3.2.data/data/resources/bdpa/germanic.tsv
malign-0.3.2.data/data/resources/bdpa/japanese.tsv
malign-0.3.2.data/data/resources/bdpa/norwegian.tsv
malign-0.3.2.data/data/resources/bdpa/ob-ugrian.tsv
malign-0.3.2.data/data/resources/bdpa/romance.tsv
malign-0.3.2.data/data/resources/bdpa/sinitic.tsv
malign-0.3.2.data/data/resources/bdpa/slavic.tsv
malign-0.3.2.data/data/resources/cmudict/README.md
malign-0.3.2.data/data/resources/cmudict/cmudict.tsv
malign-0.3.2.data/data/resources/neurodecipher/README.md
malign-0.3.2.data/data/resources/neurodecipher/greek_linearb.tsv
malign-0.3.2.data/data/resources/northeuralex/README.md
malign-0.3.2.data/data/resources/northeuralex/italic_by_cogid.tsv
malign-0.3.2.data/data/resources/northeuralex/italic_by_gloss.tsv
malign-0.3.2.data/data/resources/wiktionary/README.md
malign-0.3.2.data/data/resources/wiktionary/wiktionary.tsv
malign-0.3.2.dist-info/AUTHORS.md
malign-0.3.2.dist-info/LICENSE
malign-0.3.2.dist-info/METADATA
malign-0.3.2.dist-info/WHEEL
malign-0.3.2.dist-info/entry_points.txt
malign-0.3.2.dist-info/top_level.txt
malign-0.3.2.dist-info/RECORD
