Metadata-Version: 2.1
Name: malign
Version: 0.3.2
Summary: Library for multiple asymmetric alignments on different alphabets
Home-page: https://github.com/tresoldi/malign
Author: Tiago Tresoldi
Author-email: tiago.tresoldi@lingfil.uu.se
License: MIT
Project-URL: Documentation, https://malign.readthedocs.io
Keywords: alignment,sequence alignment,multiple alphabet
Platform: UNKNOWN
Classifier: License :: OSI Approved :: MIT License
Classifier: Operating System :: OS Independent
Classifier: Programming Language :: Python :: 3
Classifier: Topic :: Software Development :: Libraries
Requires-Python: >=3.7
Requires-Dist: networkx
Requires-Dist: numpy
Requires-Dist: sklearn
Requires-Dist: tabulate
